gurobi_optimods/__init__.py
gurobi_optimods/bipartite_matching.py
gurobi_optimods/datasets.py
gurobi_optimods/line_optimization.py
gurobi_optimods/max_flow.py
gurobi_optimods/metromap.py
gurobi_optimods/min_cost_flow.py
gurobi_optimods/min_cut.py
gurobi_optimods/mwis.py
gurobi_optimods/portfolio.py
gurobi_optimods/qubo.py
gurobi_optimods/regression.py
gurobi_optimods/sharpe_ratio.py
gurobi_optimods/utils.py
gurobi_optimods/workforce.py
gurobi_optimods/data/graphs/simple_graph_edges.csv
gurobi_optimods/data/graphs/simple_graph_nodes.csv
gurobi_optimods/data/graphs/siouxfalls_demand.csv
gurobi_optimods/data/graphs/siouxfalls_edges.csv
gurobi_optimods/data/graphs/siouxfalls_linepaths.csv
gurobi_optimods/data/graphs/siouxfalls_lines.csv
gurobi_optimods/data/graphs/siouxfalls_nodes.csv
gurobi_optimods/data/graphs/uberlin_graph.json
gurobi_optimods/data/graphs/uberlin_linepaths.csv
gurobi_optimods/data/graphs/uberlin_reduced_graph.json
gurobi_optimods/data/graphs/uberlin_reduced_linepaths.csv
gurobi_optimods/data/opf/case118.mat
gurobi_optimods/data/opf/case14.mat
gurobi_optimods/data/opf/case300.mat
gurobi_optimods/data/opf/case57.mat
gurobi_optimods/data/opf/case9-switching.mat
gurobi_optimods/data/opf/case9.mat
gurobi_optimods/data/opf/case9coords.csv
gurobi_optimods/data/opf/case9volts.csv
gurobi_optimods/data/opf/caseNY.mat
gurobi_optimods/data/opf/nybuses.csv
gurobi_optimods/data/opf/pglib_opf_case14_ieee.mat
gurobi_optimods/data/opf/pglib_opf_case3_lmbd.mat
gurobi_optimods/data/opf/pglib_opf_case5_pjm.mat
gurobi_optimods/data/portfolio/portfolio.csv
gurobi_optimods/data/sharpe-ratio/log-returns.csv
gurobi_optimods/data/workforce/preferences.csv
gurobi_optimods/data/workforce/shift_requirements.csv
gurobi_optimods/data/workforce/worker_limits.csv
gurobi_optimods/opf/__init__.py
gurobi_optimods/opf/api.py
gurobi_optimods/opf/converters.py
gurobi_optimods/opf/graphics.py
gurobi_optimods/opf/grbformulator.py
gurobi_optimods/opf/grbformulator_ac.py
gurobi_optimods-2.4.0.dist-info/METADATA
gurobi_optimods-2.4.0.dist-info/WHEEL
gurobi_optimods-2.4.0.dist-info/licenses/LICENSE
gurobi_optimods-2.4.0.dist-info/licenses/NOTICE
gurobi_optimods-2.4.0.dist-info/RECORD
