Metadata-Version: 2.4
Name: gurobi-optimods
Version: 2.4.0
Summary: Data-driven APIs for common optimization tasks
Author-email: Simon Bowly <bowly@gurobi.com>, Robert Luce <luce@gurobi.com>
License-Expression: Apache-2.0
License-File: LICENSE
License-File: NOTICE
Keywords: gurobipy,optimization,pandas,scipy
Classifier: Development Status :: 5 - Production/Stable
Classifier: Operating System :: OS Independent
Classifier: Programming Language :: Python :: 3
Classifier: Programming Language :: Python :: 3.9
Classifier: Programming Language :: Python :: 3.10
Classifier: Programming Language :: Python :: 3.11
Classifier: Programming Language :: Python :: 3.12
Classifier: Programming Language :: Python :: 3.13
Requires-Python: >=3.9
Requires-Dist: gurobipy-pandas>=1.0.0
Requires-Dist: gurobipy[matrixapi]>=11.0.0
Requires-Dist: numpy
Requires-Dist: pandas
Requires-Dist: scipy>=1.8.0
Provides-Extra: examples
Requires-Dist: matplotlib; extra == 'examples'
Requires-Dist: networkx; extra == 'examples'
Requires-Dist: plotly<6; extra == 'examples'
Requires-Dist: scikit-learn; extra == 'examples'
